envarclear/__init__.py
envarclear/envarclear.py
envarclear_karjakak-0.1.0.dist-info/METADATA
envarclear_karjakak-0.1.0.dist-info/WHEEL
envarclear_karjakak-0.1.0.dist-info/top_level.txt
envarclear_karjakak-0.1.0.dist-info/RECORD
